mkdocs_crosslink_plugin/__init__.py
mkdocs_crosslink_plugin/config.py
mkdocs_crosslink_plugin/file_cache.py
mkdocs_crosslink_plugin/plugin.py
mkdocs_crosslink_plugin/profiling.py
mkdocs_crosslink_plugin/replacer.py
mkdocs_crosslink_plugin-0.0.3.dist-info/LICENSE
mkdocs_crosslink_plugin-0.0.3.dist-info/METADATA
mkdocs_crosslink_plugin-0.0.3.dist-info/WHEEL
mkdocs_crosslink_plugin-0.0.3.dist-info/entry_points.txt
mkdocs_crosslink_plugin-0.0.3.dist-info/top_level.txt
mkdocs_crosslink_plugin-0.0.3.dist-info/RECORD
