Metadata-Version: 2.1
Name: mkdocs-crosslink-plugin
Version: 0.0.3
Summary: Simplify linking between different MkDocs sites
Home-page: https://github.com/six-two/mkdocs-crosslink-plugin
Author: six-two
Author-email: pip@six-two.dev
License: MIT License
Classifier: License :: OSI Approved :: MIT License
Classifier: Operating System :: POSIX :: Linux
Classifier: Programming Language :: Python :: 3
Classifier: Programming Language :: Python :: 3.9
Classifier: Programming Language :: Python :: 3.10
Classifier: Programming Language :: Python :: 3.11
Requires-Python: >=3.9
License-File: LICENSE
Requires-Dist: mkdocs >=1.4.0
